{
    "contrato": "400025425",
    "origen": {
        "postal": {
            "codigoPostal": "1708",
            "calle": "25 de Mayo",
            "numero": "497",
            "localidad": "Mor\u00f3n",
            "region": "",
            "pais": "Argentina",
            "componentesDeDireccion": [
                {
                    "meta": "entreCalle",
                    "contenido": "Mitre y Norberto Garc\u00eda Silva"
                }
            ]
        }
    },
    "destino": {
        "postal": {
            "codigoPostal": "1439",
            "calle": "PIEDRABUENA",
            "numero": "4890",
            "localidad": "CAPITAL FEDERAL",
            "region": "CAPITAL FEDERAL",
            "pais": "Argentina"
        }
    },
    "remitente": {
        "nombreCompleto": "Chatelet",
        "email": "chateletonline@outlook.com.ar",
        "documentoTipo": "DNI",
        "documentoNumero": "35881327",
        "telefonos": [
            {
                "tipo": 1,
                "numero": "1155042428"
            }
        ]
    },
    "destinatario": [
        {
            "nombreCompleto": "fabiana martinez",
            "email": "arqfcm@gmail.com",
            "documentoTipo": "DNI",
            "documentoNumero": "21588338",
            "telefonos": [
                {
                    "tipo": 1,
                    "numero": "1556567070"
                }
            ]
        }
    ],
    "productoAEntregar": "Compra en Chatelet",
    "bultos": [
        {
            "anchoCm": 37,
            "largoCm": 7,
            "altoCm": 30,
            "volumenCm": 7770,
            "kilos": 2,
            "valorDeclaradoSinImpuestos": "34004",
            "valorDeclaradoConImpuestos": "34004",
            "referencias": [
                {
                    "meta": "Detalle",
                    "contenido": "Compra en Chatelet"
                },
                {
                    "meta": "C\u00f3d. Cliente",
                    "contenido": "2806"
                }
            ]
        }
    ],
    "response": null
}